setupinit/__init__.py
setupinit/__main__.py
setupinit/default_files/app_init
setupinit/default_files/app_main
setupinit/default_files/gitignore
setupinit/default_files/init_py
setupinit/default_files/main_py
setupinit/default_files/manifest
setupinit/default_files/pyproject_toml
setupinit/default_files/readme
setupinit/default_files/setup_cfg
setupinit/default_files/setup_py
setupinit/default_files/tests_init
setupinit/default_files/tests_init_py
setupinit/default_files/tests_main_py
setupinit/default_files/version
setupinit/error/__init__.py
tests/__init__.py
setupinit-0.0.5.dist-info/LICENSE
setupinit-0.0.5.dist-info/METADATA
setupinit-0.0.5.dist-info/WHEEL
setupinit-0.0.5.dist-info/entry_points.txt
setupinit-0.0.5.dist-info/top_level.txt
setupinit-0.0.5.dist-info/RECORD
